{
	"cmake" : 
	{
		"generator" : 
		{
			"multiConfig" : true,
			"name" : "Visual Studio 17 2022",
			"platform" : "win32"
		},
		"paths" : 
		{
			"cmake" : "C:/Users/nolan/OneDrive - ROC Alfa-college/SotwareDevelopment/Tools/CMake/bin/cmake.exe",
			"cpack" : "C:/Users/nolan/OneDrive - ROC Alfa-college/SotwareDevelopment/Tools/CMake/bin/cpack.exe",
			"ctest" : "C:/Users/nolan/OneDrive - ROC Alfa-college/SotwareDevelopment/Tools/CMake/bin/ctest.exe",
			"root" : "C:/Users/nolan/OneDrive - ROC Alfa-college/SotwareDevelopment/Tools/CMake/share/cmake-3.30"
		},
		"version" : 
		{
			"isDirty" : false,
			"major" : 3,
			"minor" : 30,
			"patch" : 0,
			"string" : "3.30.0-rc3",
			"suffix" : "rc3"
		}
	},
	"objects" : 
	[
		{
			"jsonFile" : "codemodel-v2-f5ffc0a2f3b1f62c3aaf.json",
			"kind" : "codemodel",
			"version" : 
			{
				"major" : 2,
				"minor" : 7
			}
		},
		{
			"jsonFile" : "cache-v2-934e7ab0ac9fc0b9cede.json",
			"kind" : "cache",
			"version" : 
			{
				"major" : 2,
				"minor" : 0
			}
		},
		{
			"jsonFile" : "cmakeFiles-v1-2dd0c3e248fec40710e0.json",
			"kind" : "cmakeFiles",
			"version" : 
			{
				"major" : 1,
				"minor" : 1
			}
		},
		{
			"jsonFile" : "toolchains-v1-acafe115eed9c777ddf9.json",
			"kind" : "toolchains",
			"version" : 
			{
				"major" : 1,
				"minor" : 0
			}
		}
	],
	"reply" : 
	{
		"client-vscode" : 
		{
			"query.json" : 
			{
				"requests" : 
				[
					{
						"kind" : "cache",
						"version" : 2
					},
					{
						"kind" : "codemodel",
						"version" : 2
					},
					{
						"kind" : "toolchains",
						"version" : 1
					},
					{
						"kind" : "cmakeFiles",
						"version" : 1
					}
				],
				"responses" : 
				[
					{
						"jsonFile" : "cache-v2-934e7ab0ac9fc0b9cede.json",
						"kind" : "cache",
						"version" : 
						{
							"major" : 2,
							"minor" : 0
						}
					},
					{
						"jsonFile" : "codemodel-v2-f5ffc0a2f3b1f62c3aaf.json",
						"kind" : "codemodel",
						"version" : 
						{
							"major" : 2,
							"minor" : 7
						}
					},
					{
						"jsonFile" : "toolchains-v1-acafe115eed9c777ddf9.json",
						"kind" : "toolchains",
						"version" : 
						{
							"major" : 1,
							"minor" : 0
						}
					},
					{
						"jsonFile" : "cmakeFiles-v1-2dd0c3e248fec40710e0.json",
						"kind" : "cmakeFiles",
						"version" : 
						{
							"major" : 1,
							"minor" : 1
						}
					}
				]
			}
		}
	}
}
